[{"type": "mouse_click", "button": "left", "event_type": "down", "x": 993, "y": 531, "time": 0.9511947631835938}, {"type": "mouse_click", "button": "left", "event_type": "up", "x": 994, "y": 531, "time": 1.0362906455993652}, {"type": "mouse_click", "button": "left", "event_type": "down", "x": 1009, "y": 465, "time": 7.166499614715576}, {"type": "mouse_click", "button": "left", "event_type": "up", "x": 1009, "y": 465, "time": 7.218051910400391}, {"type": "mouse_click", "button": "left", "event_type": "down", "x": 868, "y": 531, "time": 9.866329908370972}, {"type": "mouse_click", "button": "left", "event_type": "up", "x": 868, "y": 531, "time": 9.93939757347107}, {"type": "mouse_click", "button": "left", "event_type": "down", "x": 944, "y": 270, "time": 11.379368305206299}, {"type": "mouse_click", "button": "left", "event_type": "up", "x": 944, "y": 270, "time": 11.474465608596802}, {"type": "mouse_click", "button": "left", "event_type": "down", "x": 947, "y": 373, "time": 16.63609290122986}, {"type": "mouse_click", "button": "left", "event_type": "up", "x": 947, "y": 373, "time": 16.7192165851593}, {"type": "mouse_click", "button": "left", "event_type": "down", "x": 1214, "y": 507, "time": 22.725541830062866}, {"type": "mouse_click", "button": "left", "event_type": "up", "x": 1214, "y": 507, "time": 22.811126232147217}, {"type": "mouse_click", "button": "left", "event_type": "down", "x": 1124, "y": 578, "time": 31.559656381607056}, {"type": "mouse_click", "button": "left", "event_type": "up", "x": 1124, "y": 578, "time": 31.629225254058838}, {"type": "key_event", "key": "esc", "event_type": "down", "time": 35.60289406776428}]